LICENSE.txt
README.txt
setup.cfg
setup.py
docs/HISTORY.txt
haufe/__init__.py
haufe.ztop.egg-info/PKG-INFO
haufe.ztop.egg-info/SOURCES.txt
haufe.ztop.egg-info/dependency_links.txt
haufe.ztop.egg-info/entry_points.txt
haufe.ztop.egg-info/namespace_packages.txt
haufe.ztop.egg-info/not-zip-safe
haufe.ztop.egg-info/requires.txt
haufe.ztop.egg-info/top_level.txt
haufe/ztop/Feeder.py
haufe/ztop/Sampler.py
haufe/ztop/__init__.py
haufe/ztop/zanalyse.py
haufe/ztop/ztop.py