Metadata-Version: 1.0
Name: haufe.ztop
Version: 0.2.2
Summary: Real-time Zope request analysis based on haufe.requestmonitoring
Home-page: UNKNOWN
Author: Andreas Jung
Author-email: info@zopyx.com
License: ZPL (see LICENSE.txt)
Platform: UNKNOWN
Classifier: Programming Language :: Python
Classifier: Framework :: Zope2
Classifier: Topic :: System :: Monitoring
Classifier: Topic :: System :: Logging
